jnlog.py
jnlog-1.0.3.dist-info/LICENSE
jnlog-1.0.3.dist-info/METADATA
jnlog-1.0.3.dist-info/WHEEL
jnlog-1.0.3.dist-info/top_level.txt
jnlog-1.0.3.dist-info/RECORD
