Metadata-Version: 2.1
Name: jnlog
Version: 1.0.3
Summary: jnlog simple colored text logger for python
Home-page: https://gitlab.com/seeklay/jnlog
Author: seeklay
License: UNKNOWN
Platform: UNKNOWN
License-File: LICENSE
